fastapi_yieldable_response/__init__.py
fastapi_yieldable_response-0.1.0.dist-info/METADATA
fastapi_yieldable_response-0.1.0.dist-info/WHEEL
fastapi_yieldable_response-0.1.0.dist-info/licenses/LICENSE
fastapi_yieldable_response-0.1.0.dist-info/RECORD
