Metadata-Version: 2.4
Name: fastapi_yieldable_response
Version: 0.1.0
Summary: A middleware for FastAPI that sends early responses from route handlers.
Project-URL: Homepage, https://github.com/lucamattiazzi/fastapi_yieldable_response
Project-URL: Repository, https://github.com/lucamattiazzi/fastapi_yieldable_response
Project-URL: Issues, https://github.com/lucamattiazzi/fastapi_yieldable_response/issues
Author-email: Luca Mattiazzi <l.d.mattiazzi@gmail.com>
License: MIT
License-File: LICENSE
Keywords: fastapi
Classifier: Development Status :: 4 - Beta
Classifier: Framework :: FastAPI
Classifier: Intended Audience :: Developers
Classifier: License :: OSI Approved :: MIT License
Classifier: Programming Language :: Python :: 3
Classifier: Programming Language :: Python :: 3.10
Classifier: Programming Language :: Python :: 3.11
Classifier: Programming Language :: Python :: 3.12
Classifier: Programming Language :: Python :: 3.13
Classifier: Topic :: Internet :: WWW/HTTP
Classifier: Topic :: Software Development :: Libraries :: Python Modules
Requires-Python: >=3.10
Requires-Dist: fastapi>=0.68.0
